CHANGES
MANIFEST.in
README.rst
ez_setup.py
setup.cfg
setup.py
./cykooz/__init__.py
./cykooz/buildout/__init__.py
./cykooz/buildout/basicauth/__init__.py
./cykooz/buildout/basicauth/credentials.py
./cykooz/buildout/basicauth/download.py
./cykooz/buildout/basicauth/fetchers.py
./cykooz/buildout/basicauth/protected_ext.py
./cykooz/buildout/basicauth/tests/__init__.py
./cykooz/buildout/basicauth/tests/test_credentials.py
./cykooz/buildout/basicauth/tests/test_download.py
./cykooz/buildout/basicauth/tests/test_fetchers.py
cykooz.buildout.basicauth.egg-info/PKG-INFO
cykooz.buildout.basicauth.egg-info/SOURCES.txt
cykooz.buildout.basicauth.egg-info/dependency_links.txt
cykooz.buildout.basicauth.egg-info/entry_points.txt
cykooz.buildout.basicauth.egg-info/namespace_packages.txt
cykooz.buildout.basicauth.egg-info/not-zip-safe
cykooz.buildout.basicauth.egg-info/requires.txt
cykooz.buildout.basicauth.egg-info/top_level.txt