Metadata-Version: 1.0
Name: cykooz.buildout.basicauth
Version: 0.1.1
Summary: Buildout extension providing basic authentication support
Home-page: https://bitbucket.org/cykooz/cykooz.buildout.basicauth
Author: Kirill Kuzminykh
Author-email: saikuz@mail.ru
License: Apache Public License
Keywords: buildout basicauth http authentication
Platform: UNKNOWN
